nuttlib/__init__.py
nuttlib/layer.py
nuttlib/mat.py
nuttlib/network.py
nuttlib/neuron.py
nuttlib/ops.py
nuttlib/randomizer.py
nuttlib/trainer.py
NUTT-0.0.15.dist-info/METADATA
NUTT-0.0.15.dist-info/WHEEL
NUTT-0.0.15.dist-info/top_level.txt
NUTT-0.0.15.dist-info/RECORD
