Metadata-Version: 2.1
Name: NUTT
Version: 0.0.15
Summary: A custom machine learning library
Home-page: https://github.com/simonSlamka/NUTT
Author: Simon Slamka
Author-email: simon.slamka@ongakken.com
Requires-Dist: termcolor
